setup.py
shinkenplugins/__init__.py
shinkenplugins.plugins.bixi_montreal.egg-info/PKG-INFO
shinkenplugins.plugins.bixi_montreal.egg-info/SOURCES.txt
shinkenplugins.plugins.bixi_montreal.egg-info/dependency_links.txt
shinkenplugins.plugins.bixi_montreal.egg-info/namespace_packages.txt
shinkenplugins.plugins.bixi_montreal.egg-info/requires.txt
shinkenplugins.plugins.bixi_montreal.egg-info/top_level.txt
shinkenplugins/plugins/__init__.py
shinkenplugins/plugins/bixi_montreal/__init__.py
shinkenplugins/plugins/bixi_montreal/bixi_montreal.py