Metadata-Version: 1.0
Name: shinkenplugins.plugins.bixi-montreal
Version: 1.2
Summary: Check Montréal Bixi
Home-page: https://github.com/savoirfairelinux/sfl-shinken-plugins
Author: Savoir-faire Linux
Author-email: supervision@savoirfairelinux.com
License: GPL3+
Platform: any
